MANIFEST.in
README.txt
setup.py
docs/HISTORY.txt
src/infrae/__init__.py
src/infrae.cache.egg-info/PKG-INFO
src/infrae.cache.egg-info/SOURCES.txt
src/infrae.cache.egg-info/dependency_links.txt
src/infrae.cache.egg-info/entry_points.txt
src/infrae.cache.egg-info/namespace_packages.txt
src/infrae.cache.egg-info/not-zip-safe
src/infrae.cache.egg-info/requires.txt
src/infrae.cache.egg-info/top_level.txt
src/infrae/cache/__init__.py
src/infrae/cache/beakerext/__init__.py
src/infrae/cache/beakerext/lru.py
src/infrae/cache/beakerext/nocache.py