Metadata-Version: 1.0
Name: infrae.cache
Version: 1.0
Summary: Infrae cache utilities
Home-page: http://hg.infrae.com/infrae.cache
Author: Infrae
Author-email: info@infrae.com
License: ZPL
Keywords: zope2 resourceinclude z3c
Platform: UNKNOWN
Classifier: Environment :: Web Environment
Classifier: Intended Audience :: Developers
Classifier: License :: OSI Approved :: Zope Public License
Classifier: Programming Language :: Python
Classifier: Topic :: Software Development :: Libraries :: Python Modules
